stacked_generalization/__init__.py
stacked_generalization/lib/__init__.py
stacked_generalization/lib/joblibed.py
stacked_generalization/lib/stacking.py
stacked_generalization/lib/util.py
stacked_generalization-0.0.6.dist-info/DESCRIPTION.rst
stacked_generalization-0.0.6.dist-info/METADATA
stacked_generalization-0.0.6.dist-info/RECORD
stacked_generalization-0.0.6.dist-info/WHEEL
stacked_generalization-0.0.6.dist-info/metadata.json
stacked_generalization-0.0.6.dist-info/top_level.txt
