Metadata-Version: 2.0
Name: stacked-generalization
Version: 0.0.6
Summary: Machine Learning Stacking Util
Home-page: https://github.com/fukatani/stacked_generalization
Author: Ryosuke Fukatani
Author-email: nannyakannya@gmail.com
License: Apache License 2.0
Keywords: Stacking,Machine Learning
Platform: UNKNOWN
Requires-Dist: numpy
Requires-Dist: pandas
Requires-Dist: scikit-learn
